{"body":{"manifests":{"doctrine\/annotations":{"manifest":{"conflict":{"symfony\/routing":"<6.0"}},"files":[],"ref":"64d8583af5ea57b7afa4aba4b159907f3a148b05"}}},"headers":{"content-length":["168"],"source-age":["0"],"expires":["Mon, 06 Mar 2023 17:29:55 GMT"],"x-fastly-request-id":["b676c3c4314e955e6bff18154ea1abb6c49cfac2"],"access-control-allow-origin":["*"],"vary":["Authorization,Accept-Encoding,Origin"],"x-timer":["S1678123495.040130,VS0,VE184"],"x-cache-hits":["0"],"x-cache":["MISS"],"x-served-by":["cache-bog2260035-BOG"],"via":["1.1 varnish"],"date":["Mon, 06 Mar 2023 17:24:55 GMT"],"accept-ranges":["bytes"],"content-encoding":["gzip"],"x-github-request-id":["7DEE:27E5:0170:0BD6:640621E7"],"x-xss-protection":["1; mode=block"],"x-frame-options":["deny"],"x-content-type-options":["nosniff"],"strict-transport-security":["max-age=31536000"],"etag":["W\/\"6efd31d1d53118ad64812c905f78fcb658ac48120c2e1667c8f3a2a79e30ec72\""],"content-type":["text\/plain; charset=utf-8"],"content-security-policy":["default-src 'none'; style-src 'unsafe-inline'; sandbox"],"cache-control":["max-age=300"]}}